[
    {
        "station": "MONTPELLIER",
        "geo": [
            3.880674,
            43.604738
        ],
        "name": "Montpellier Saint-Roch",
        "city": "Montpellier",
        "uic": "0087773002"
    },
    {
        "station": "ANNECY",
        "geo": [
            6.121835,
            45.901965
        ],
        "name": "Annecy",
        "city": "Annecy",
        "uic": "0087746008"
    },
    {
        "station": "BORDEAUX ST JEAN",
        "geo": [
            -0.556697,
            44.825873
        ],
        "name": "Bordeaux Saint-Jean",
        "city": "Bordeaux",
        "uic": "0087581009"
    },
    {
        "station": "LE MANS",
        "geo": [
            0.192578,
            47.995689
        ],
        "name": "Le Mans",
        "city": "Mans",
        "uic": "0087396002"
    },
    {
        "station": "TOURCOING",
        "geo": [
            3.16804,
            50.71683
        ],
        "name": "Tourcoing",
        "city": "Tourcoing",
        "uic": "0087286542"
    },
    {
        "station": "PERPIGNAN",
        "geo": [
            2.879779,
            42.696292
        ],
        "name": "Perpignan",
        "city": "Perpignan",
        "uic": "0087784009"
    },
    {
        "station": "LYON PART DIEU",
        "geo": [
            4.859355,
            45.760559
        ],
        "name": "Lyon Part Dieu",
        "city": "Lyon",
        "uic": "0087723197"
    },
    {
        "station": "ANGOULEME",
        "geo": [
            0.164608,
            45.653572
        ],
        "name": "Angoul\u00eame",
        "city": "Angoul\u00eame",
        "uic": "0087583005"
    },
    {
        "station": "ST PIERRE DES CORPS",
        "geo": [
            0.72355,
            47.386099
        ],
        "name": "Saint-Pierre-des-Corps",
        "city": "Saint-Pierre-des-Corps",
        "uic": "0087571240"
    },
    {
        "station": "NANTES",
        "geo": [
            -1.542356,
            47.216148
        ],
        "name": "Nantes",
        "city": "Nantes",
        "uic": "0087481002"
    },
    {
        "station": "BREST",
        "geo": [
            -4.478903,
            48.38811
        ],
        "name": "Brest",
        "city": "Brest",
        "uic": "0087474007"
    },
    {
        "station": "PARIS NORD",
        "geo": [
            2.355151,
            48.880185
        ],
        "name": "Paris Gare du Nord",
        "city": "Paris",
        "uic": "0087271031"
    },
    {
        "station": "NIMES",
        "geo": [
            4.365845,
            43.832291
        ],
        "name": "N\u00eemes",
        "city": "N\u00eemes",
        "uic": "0087775007"
    },
    {
        "station": "TOULON",
        "geo": [
            5.929293,
            43.12837
        ],
        "name": "Toulon",
        "city": "Toulon",
        "uic": "0087755009"
    },
    {
        "station": "DIJON VILLE",
        "geo": [
            5.027208,
            47.32337
        ],
        "name": "Dijon",
        "city": "Dijon",
        "uic": "0087713040"
    },
    {
        "station": "QUIMPER",
        "geo": [
            -4.092103,
            47.994455
        ],
        "name": "Quimper",
        "city": "Quimper",
        "uic": "0087474098"
    },
    {
        "station": "PARIS MONTPARNASSE",
        "geo": [
            2.320514,
            48.841172
        ],
        "name": "Paris Montparnasse",
        "city": "Paris",
        "uic": "0087391102"
    },
    {
        "station": "ARRAS",
        "geo": [
            2.781942,
            50.286673
        ],
        "name": "Arras",
        "city": "Arras",
        "uic": "0087342014"
    },
    {
        "station": "AIX EN PROVENCE TGV",
        "geo": [
            5.317534,
            43.455237
        ],
        "name": "Aix-en-Provence TGV",
        "city": "Aix-en-Provence",
        "uic": "0087319012"
    },
    {
        "station": "NICE VILLE",
        "geo": [
            7.261904,
            43.704556
        ],
        "name": "Nice",
        "city": "Nice",
        "uic": "0087756056"
    },
    {
        "station": "CHAMBERY CHALLES LES EAUX",
        "geo": [
            5.919547,
            45.571302
        ],
        "name": "Chamb\u00e9ry - Challes-les-Eaux",
        "city": "Chamb\u00e9ry",
        "uic": "0087741009"
    },
    {
        "station": "POITIERS",
        "geo": [
            0.333241,
            46.582275
        ],
        "name": "Poitiers",
        "city": "Poitiers",
        "uic": "0087575001"
    },
    {
        "station": "LA ROCHELLE VILLE",
        "geo": [
            -1.145305,
            46.15269
        ],
        "name": "La Rochelle",
        "city": "Rochelle",
        "uic": "0087485003"
    },
    {
        "station": "ST MALO",
        "geo": [
            -2.004158,
            48.646859
        ],
        "name": "Saint-Malo",
        "city": "Saint-Malo",
        "uic": "0087478107"
    },
    {
        "station": "VANNES",
        "geo": [
            -2.75245,
            47.665169
        ],
        "name": "Vannes",
        "city": "Vannes",
        "uic": "0087476606"
    },
    {
        "station": "RENNES",
        "geo": [
            -1.672744,
            48.103517
        ],
        "name": "Rennes",
        "city": "Rennes",
        "uic": "0087471003"
    },
    {
        "station": "AVIGNON TGV",
        "geo": [
            4.786079,
            43.921586
        ],
        "name": "Avignon TGV",
        "city": "Avignon",
        "uic": "0087318964"
    },
    {
        "station": "DUNKERQUE",
        "geo": [
            2.368961,
            51.03047
        ],
        "name": "Dunkerque",
        "city": "Dunkerque",
        "uic": "0087281006"
    },
    {
        "station": "PARIS NORD",
        "geo": [
            2.355151,
            48.880185
        ],
        "name": "Paris Gare du Nord",
        "city": "Paris",
        "uic": "0087271007"
    },
    {
        "station": "STRASBOURG",
        "geo": [
            7.734584,
            48.584967
        ],
        "name": "Strasbourg",
        "city": "Strasbourg",
        "uic": "0087212027"
    },
    {
        "station": "MULHOUSE VILLE",
        "geo": [
            7.342396,
            47.742224
        ],
        "name": "Mulhouse",
        "city": "Mulhouse",
        "uic": "0087182063"
    },
    {
        "station": "REIMS",
        "geo": [
            4.024435,
            49.258978
        ],
        "name": "Reims",
        "city": "Reims",
        "uic": "0087171009"
    },
    {
        "station": "PARIS EST",
        "geo": [
            2.358424,
            48.876742
        ],
        "name": "Paris Est",
        "city": "Paris",
        "uic": "0087113001"
    },
    {
        "station": "MARSEILLE ST CHARLES",
        "geo": [
            5.380407,
            43.302666
        ],
        "name": "Marseille Saint-Charles",
        "city": "Marseille",
        "uic": "0087751008"
    },
    {
        "station": "GRENOBLE",
        "geo": [
            5.714584,
            45.191493
        ],
        "name": "Grenoble",
        "city": "Grenoble",
        "uic": "0087747006"
    },
    {
        "station": "TOULOUSE MATABIAU",
        "geo": [
            1.453616,
            43.611206
        ],
        "name": "Toulouse Matabiau",
        "city": "Toulouse",
        "uic": "0087611004"
    },
    {
        "station": "TOURS",
        "geo": [
            0.693703,
            47.389781
        ],
        "name": "Tours",
        "city": "Tours",
        "uic": "0087571000"
    },
    {
        "station": "LAVAL",
        "geo": [
            -0.760907,
            48.076206
        ],
        "name": "Laval",
        "city": "Laval",
        "uic": "0087478404"
    },
    {
        "station": "PARIS MONTPARNASSE",
        "geo": [
            2.320514,
            48.841172
        ],
        "name": "Paris Montparnasse",
        "city": "Paris",
        "uic": "0087391003"
    },
    {
        "station": "DOUAI",
        "geo": [
            3.089986,
            50.371677
        ],
        "name": "Douai",
        "city": "Douai",
        "uic": "0087345009"
    }
]